LICENSE
README.md
pyproject.toml
setup.py
py_cz_api/ApiExtended.py
py_cz_api/__init__.py
py_cz_api/_typing.py
py_cz_api/_utils.py
py_cz_api/apis.py
py_cz_api/certificates.py
py_cz_api/documents.py
py_cz_api/exceptions.py
py_cz_api/tokens.py
py_cz_api.egg-info/PKG-INFO
py_cz_api.egg-info/SOURCES.txt
py_cz_api.egg-info/dependency_links.txt
py_cz_api.egg-info/requires.txt
py_cz_api.egg-info/top_level.txt