Metadata-Version: 2.1
Name: py_cz_api
Version: 0.3.0
Summary: Библиотека для автоматизации работы с Честным Знаком через True API
Home-page: https://github.com/jqxl/py_cz_api
Download-URL: https://codeload.github.com/jqxl/py_cz_api/zip/refs/heads/main
Author: jqxl
Author-email: jqxl+git@ya.ru
License: GNU General Public License v3.0
Classifier: Programming Language :: Python :: 3
Requires-Python: >=3.10
License-File: LICENSE
Requires-Dist: aiohttp
Requires-Dist: pandas
Requires-Dist: PyJWT
Requires-Dist: requests
Requires-Dist: pywin32
